HDDFeatSelection/__init__.py
HDDFeatSelection/discernibleScore.py
HDDFeatSelection/fastFeatureSelectionDS.py
HDDFeatSelection/increDiscernibleScore.py
HDDFeatSelection/increFeaSltDSFilterSam.py
HDDFeatSelection/increFeatureSelectionDS.py
HDDFeatSelection/partition_fold.py
HDDFeatSelection-0.1.1.dist-info/METADATA
HDDFeatSelection-0.1.1.dist-info/WHEEL
HDDFeatSelection-0.1.1.dist-info/top_level.txt
HDDFeatSelection-0.1.1.dist-info/RECORD
